LICENSE
README.md
pyproject.toml
setup.cfg
setup.py
python_docker/__init__.py
python_docker/base.py
python_docker/docker.py
python_docker/registry.py
python_docker/schema.py
python_docker/tar.py
python_docker/utils.py
python_docker.egg-info/PKG-INFO
python_docker.egg-info/SOURCES.txt
python_docker.egg-info/dependency_links.txt
python_docker.egg-info/requires.txt
python_docker.egg-info/top_level.txt
tests/__init__.py
tests/test_docker_image.py
tests/test_integration.py
tests/test_registry.py