Metadata-Version: 2.1
Name: python-docker
Version: 0.2.0
Summary: Python Docker
Home-page: https://github.com/costrou/python-docker
Author: Christopher Ostrouchov
Author-email: chris.ostrouchov@gmail.com
License: UNKNOWN
Project-URL: Bug Reports, https://github.com/costrouc/python-docker
Project-URL: Source, https://github.com/costrouc/python-docker
Keywords: conda,docker
Platform: UNKNOWN
Classifier: Development Status :: 3 - Alpha
Classifier: Intended Audience :: Developers
Classifier: Topic :: Software Development :: Build Tools
Classifier: License :: OSI Approved :: BSD License
Classifier: Programming Language :: Python :: 3
Classifier: Programming Language :: Python :: 3.8
Classifier: Programming Language :: Python :: 3.9
Classifier: Programming Language :: Python :: 3.10
Classifier: Programming Language :: Python :: 3 :: Only
Provides-Extra: dev
